<?xml version="1.0" encoding="utf-8"?>
<namespace name="ATXPVS" platform="Win32">
  <const name="WP_CAPTION" type="Integer" file="ATXPVS.pas" line="38">
    <value>
      $1
    </value>
  </const>
  <const name="WP_SMALLCAPTION" type="Integer" file="ATXPVS.pas" line="40">
    <value>
      $2
    </value>
  </const>
  <const name="WP_MINCAPTION" type="Integer" file="ATXPVS.pas" line="42">
    <value>
      $3
    </value>
  </const>
  <const name="WP_SMALLMINCAPTION" type="Integer" file="ATXPVS.pas" line="44">
    <value>
      $4
    </value>
  </const>
  <const name="WP_MAXCAPTION" type="Integer" file="ATXPVS.pas" line="46">
    <value>
      $5
    </value>
  </const>
  <const name="WP_SMALLMAXCAPTION" type="Integer" file="ATXPVS.pas" line="48">
    <value>
      $6
    </value>
  </const>
  <const name="WP_FRAMELEFT" type="Integer" file="ATXPVS.pas" line="50">
    <value>
      $7
    </value>
  </const>
  <const name="WP_FRAMERIGHT" type="Integer" file="ATXPVS.pas" line="52">
    <value>
      $8
    </value>
  </const>
  <const name="WP_FRAMEBOTTOM" type="Integer" file="ATXPVS.pas" line="54">
    <value>
      $9
    </value>
  </const>
  <const name="WP_SMALLFRAMELEFT" type="Integer" file="ATXPVS.pas" line="56">
    <value>
      $A
    </value>
  </const>
  <const name="WP_SMALLFRAMERIGHT" type="Integer" file="ATXPVS.pas" line="58">
    <value>
      $B
    </value>
  </const>
  <const name="WP_SMALLFRAMEBOTTOM" type="Integer" file="ATXPVS.pas" line="60">
    <value>
      $C
    </value>
  </const>
  <const name="WP_SYSBUTTON" type="Integer" file="ATXPVS.pas" line="64">
    <value>
      $D
    </value>
  </const>
  <const name="WP_MDISYSBUTTON" type="Integer" file="ATXPVS.pas" line="66">
    <value>
      $E
    </value>
  </const>
  <const name="WP_MINBUTTON" type="Integer" file="ATXPVS.pas" line="68">
    <value>
      $F
    </value>
  </const>
  <const name="WP_MDIMINBUTTON" type="Integer" file="ATXPVS.pas" line="71">
    <value>
      $10
    </value>
  </const>
  <const name="WP_MAXBUTTON" type="Integer" file="ATXPVS.pas" line="73">
    <value>
      $11
    </value>
  </const>
  <const name="WP_CLOSEBUTTON" type="Integer" file="ATXPVS.pas" line="75">
    <value>
      $12
    </value>
  </const>
  <const name="WP_SMALLCLOSEBUTTON" type="Integer" file="ATXPVS.pas" line="77">
    <value>
      $13
    </value>
  </const>
  <const name="WP_MDICLOSEBUTTON" type="Integer" file="ATXPVS.pas" line="79">
    <value>
      $14
    </value>
  </const>
  <const name="WP_RESTOREBUTTON" type="Integer" file="ATXPVS.pas" line="81">
    <value>
      $15
    </value>
  </const>
  <const name="WP_MDIRESTOREBUTTON" type="Integer" file="ATXPVS.pas" line="83">
    <value>
      $16
    </value>
  </const>
  <const name="WP_HELPBUTTON" type="Integer" file="ATXPVS.pas" line="85">
    <value>
      $17
    </value>
  </const>
  <const name="WP_MDIHELPBUTTON" type="Integer" file="ATXPVS.pas" line="87">
    <value>
      $18
    </value>
  </const>
  <const name="WP_HORZSCROLL" type="Integer" file="ATXPVS.pas" line="90">
    <value>
      $19
    </value>
  </const>
  <const name="WP_HORZTHUMB" type="Integer" file="ATXPVS.pas" line="92">
    <value>
      $1A
    </value>
  </const>
  <const name="WP_VERTSCROLL" type="Integer" file="ATXPVS.pas" line="94">
    <value>
      $1B
    </value>
  </const>
  <const name="WP_VERTTHUMB" type="Integer" file="ATXPVS.pas" line="96">
    <value>
      $1C
    </value>
  </const>
  <const name="WP_DIALOG" type="Integer" file="ATXPVS.pas" line="99">
    <value>
      $1D
    </value>
  </const>
  <const name="WP_CAPTIONSIZINGTEMPLATE" type="Integer" file="ATXPVS.pas" line="102">
    <value>
      $1E
    </value>
  </const>
  <const name="WP_SMALLCAPTIONSIZINGTEMPLATE" type="Integer" file="ATXPVS.pas" line="104">
    <value>
      $1F
    </value>
  </const>
  <const name="WP_FRAMELEFTSIZINGTEMPLATE" type="Integer" file="ATXPVS.pas" line="106">
    <value>
      $20
    </value>
  </const>
  <const name="WP_SMALLFRAMELEFTSIZINGTEMPLATE" type="Integer" file="ATXPVS.pas" line="108">
    <value>
      $21
    </value>
  </const>
  <const name="WP_FRAMERIGHTSIZINGTEMPLATE" type="Integer" file="ATXPVS.pas" line="110">
    <value>
      $22
    </value>
  </const>
  <const name="WP_SMALLFRAMERIGHTSIZINGTEMPLATE" type="Integer" file="ATXPVS.pas" line="112">
    <value>
      $23
    </value>
  </const>
  <const name="WP_FRAMEBOTTOMSIZINGTEMPLATE" type="Integer" file="ATXPVS.pas" line="114">
    <value>
      $24
    </value>
  </const>
  <const name="WP_SMALLFRAMEBOTTOMSIZINGTEMPLATE" type="Integer" file="ATXPVS.pas" line="116">
    <value>
      $25
    </value>
  </const>
  <const name="FS_ACTIVE" type="Integer" file="ATXPVS.pas" line="119">
    <value>
      $1
    </value>
  </const>
  <const name="FS_INACTIVE" type="Integer" file="ATXPVS.pas" line="121">
    <value>
      $2
    </value>
  </const>
  <const name="CS_ACTIVE" type="Integer" file="ATXPVS.pas" line="124">
    <value>
      $1
    </value>
  </const>
  <const name="CS_INACTIVE" type="Integer" file="ATXPVS.pas" line="126">
    <value>
      $2
    </value>
  </const>
  <const name="CS_DISABLED" type="Integer" file="ATXPVS.pas" line="128">
    <value>
      $3
    </value>
  </const>
  <const name="MXCS_ACTIVE" type="Integer" file="ATXPVS.pas" line="131">
    <value>
      $1
    </value>
  </const>
  <const name="MXCS_INACTIVE" type="Integer" file="ATXPVS.pas" line="133">
    <value>
      $2
    </value>
  </const>
  <const name="MXCS_DISABLED" type="Integer" file="ATXPVS.pas" line="135">
    <value>
      $3
    </value>
  </const>
  <const name="MNCS_ACTIVE" type="Integer" file="ATXPVS.pas" line="138">
    <value>
      $1
    </value>
  </const>
  <const name="MNCS_INACTIVE" type="Integer" file="ATXPVS.pas" line="140">
    <value>
      $2
    </value>
  </const>
  <const name="MNCS_DISABLED" type="Integer" file="ATXPVS.pas" line="142">
    <value>
      $3
    </value>
  </const>
  <const name="HSS_NORMAL" type="Integer" file="ATXPVS.pas" line="145">
    <value>
      $1
    </value>
  </const>
  <const name="HSS_HOT" type="Integer" file="ATXPVS.pas" line="147">
    <value>
      $2
    </value>
  </const>
  <const name="HSS_PUSHED" type="Integer" file="ATXPVS.pas" line="149">
    <value>
      $3
    </value>
  </const>
  <const name="HSS_DISABLED" type="Integer" file="ATXPVS.pas" line="151">
    <value>
      $4
    </value>
  </const>
  <const name="HTS_NORMAL" type="Integer" file="ATXPVS.pas" line="154">
    <value>
      $1
    </value>
  </const>
  <const name="HTS_HOT" type="Integer" file="ATXPVS.pas" line="156">
    <value>
      $2
    </value>
  </const>
  <const name="HTS_PUSHED" type="Integer" file="ATXPVS.pas" line="158">
    <value>
      $3
    </value>
  </const>
  <const name="HTS_DISABLED" type="Integer" file="ATXPVS.pas" line="160">
    <value>
      $4
    </value>
  </const>
  <const name="VSS_NORMAL" type="Integer" file="ATXPVS.pas" line="163">
    <value>
      $1
    </value>
  </const>
  <const name="VSS_HOT" type="Integer" file="ATXPVS.pas" line="165">
    <value>
      $2
    </value>
  </const>
  <const name="VSS_PUSHED" type="Integer" file="ATXPVS.pas" line="167">
    <value>
      $3
    </value>
  </const>
  <const name="VSS_DISABLED" type="Integer" file="ATXPVS.pas" line="169">
    <value>
      $4
    </value>
  </const>
  <const name="VTS_NORMAL" type="Integer" file="ATXPVS.pas" line="172">
    <value>
      $1
    </value>
  </const>
  <const name="VTS_HOT" type="Integer" file="ATXPVS.pas" line="174">
    <value>
      $2
    </value>
  </const>
  <const name="VTS_PUSHED" type="Integer" file="ATXPVS.pas" line="176">
    <value>
      $3
    </value>
  </const>
  <const name="VTS_DISABLED" type="Integer" file="ATXPVS.pas" line="178">
    <value>
      $4
    </value>
  </const>
  <const name="SBS_NORMAL" type="Integer" file="ATXPVS.pas" line="181">
    <value>
      $1
    </value>
  </const>
  <const name="SBS_HOT" type="Integer" file="ATXPVS.pas" line="183">
    <value>
      $2
    </value>
  </const>
  <const name="SBS_PUSHED" type="Integer" file="ATXPVS.pas" line="185">
    <value>
      $3
    </value>
  </const>
  <const name="SBS_DISABLED" type="Integer" file="ATXPVS.pas" line="187">
    <value>
      $4
    </value>
  </const>
  <const name="MINBS_NORMAL" type="Integer" file="ATXPVS.pas" line="190">
    <value>
      $1
    </value>
  </const>
  <const name="MINBS_HOT" type="Integer" file="ATXPVS.pas" line="192">
    <value>
      $2
    </value>
  </const>
  <const name="MINBS_PUSHED" type="Integer" file="ATXPVS.pas" line="194">
    <value>
      $3
    </value>
  </const>
  <const name="MINBS_DISABLED" type="Integer" file="ATXPVS.pas" line="196">
    <value>
      $4
    </value>
  </const>
  <const name="MAXBS_NORMAL" type="Integer" file="ATXPVS.pas" line="199">
    <value>
      $1
    </value>
  </const>
  <const name="MAXBS_HOT" type="Integer" file="ATXPVS.pas" line="201">
    <value>
      $2
    </value>
  </const>
  <const name="MAXBS_PUSHED" type="Integer" file="ATXPVS.pas" line="203">
    <value>
      $3
    </value>
  </const>
  <const name="MAXBS_DISABLED" type="Integer" file="ATXPVS.pas" line="205">
    <value>
      $4
    </value>
  </const>
  <const name="RBS_NORMAL" type="Integer" file="ATXPVS.pas" line="208">
    <value>
      $1
    </value>
  </const>
  <const name="RBS_HOT" type="Integer" file="ATXPVS.pas" line="210">
    <value>
      $2
    </value>
  </const>
  <const name="RBS_PUSHED" type="Integer" file="ATXPVS.pas" line="212">
    <value>
      $3
    </value>
  </const>
  <const name="RBS_DISABLED" type="Integer" file="ATXPVS.pas" line="214">
    <value>
      $4
    </value>
  </const>
  <const name="HBS_NORMAL" type="Integer" file="ATXPVS.pas" line="217">
    <value>
      $1
    </value>
  </const>
  <const name="HBS_HOT" type="Integer" file="ATXPVS.pas" line="219">
    <value>
      $2
    </value>
  </const>
  <const name="HBS_PUSHED" type="Integer" file="ATXPVS.pas" line="221">
    <value>
      $3
    </value>
  </const>
  <const name="HBS_DISABLED" type="Integer" file="ATXPVS.pas" line="223">
    <value>
      $4
    </value>
  </const>
  <const name="CBS_NORMAL" type="Integer" file="ATXPVS.pas" line="226">
    <value>
      $1
    </value>
  </const>
  <const name="CBS_HOT" type="Integer" file="ATXPVS.pas" line="228">
    <value>
      $2
    </value>
  </const>
  <const name="CBS_PUSHED" type="Integer" file="ATXPVS.pas" line="230">
    <value>
      $3
    </value>
  </const>
  <const name="CBS_DISABLED" type="Integer" file="ATXPVS.pas" line="232">
    <value>
      $4
    </value>
  </const>
  <const name="BP_PUSHBUTTON" type="Integer" file="ATXPVS.pas" line="238">
    <value>
      $1
    </value>
  </const>
  <const name="BP_RADIOBUTTON" type="Integer" file="ATXPVS.pas" line="240">
    <value>
      $2
    </value>
  </const>
  <const name="BP_CHECKBOX" type="Integer" file="ATXPVS.pas" line="242">
    <value>
      $3
    </value>
  </const>
  <const name="BP_GROUPBOX" type="Integer" file="ATXPVS.pas" line="244">
    <value>
      $4
    </value>
  </const>
  <const name="BP_USERBUTTON" type="Integer" file="ATXPVS.pas" line="246">
    <value>
      $5
    </value>
  </const>
  <const name="PBS_NORMAL" type="Integer" file="ATXPVS.pas" line="249">
    <value>
      $1
    </value>
  </const>
  <const name="PBS_HOT" type="Integer" file="ATXPVS.pas" line="251">
    <value>
      $2
    </value>
  </const>
  <const name="PBS_PRESSED" type="Integer" file="ATXPVS.pas" line="253">
    <value>
      $3
    </value>
  </const>
  <const name="PBS_DISABLED" type="Integer" file="ATXPVS.pas" line="255">
    <value>
      $4
    </value>
  </const>
  <const name="PBS_DEFAULTED" type="Integer" file="ATXPVS.pas" line="257">
    <value>
      $5
    </value>
  </const>
  <const name="RBS_UNCHECKEDNORMAL" type="Integer" file="ATXPVS.pas" line="260">
    <value>
      $1
    </value>
  </const>
  <const name="RBS_UNCHECKEDHOT" type="Integer" file="ATXPVS.pas" line="262">
    <value>
      $2
    </value>
  </const>
  <const name="RBS_UNCHECKEDPRESSED" type="Integer" file="ATXPVS.pas" line="264">
    <value>
      $3
    </value>
  </const>
  <const name="RBS_UNCHECKEDDISABLED" type="Integer" file="ATXPVS.pas" line="266">
    <value>
      $4
    </value>
  </const>
  <const name="RBS_CHECKEDNORMAL" type="Integer" file="ATXPVS.pas" line="268">
    <value>
      $5
    </value>
  </const>
  <const name="RBS_CHECKEDHOT" type="Integer" file="ATXPVS.pas" line="270">
    <value>
      $6
    </value>
  </const>
  <const name="RBS_CHECKEDPRESSED" type="Integer" file="ATXPVS.pas" line="272">
    <value>
      $7
    </value>
  </const>
  <const name="RBS_CHECKEDDISABLED" type="Integer" file="ATXPVS.pas" line="274">
    <value>
      $8
    </value>
  </const>
  <const name="CBS_UNCHECKEDNORMAL" type="Integer" file="ATXPVS.pas" line="277">
    <value>
      $1
    </value>
  </const>
  <const name="CBS_UNCHECKEDHOT" type="Integer" file="ATXPVS.pas" line="279">
    <value>
      $2
    </value>
  </const>
  <const name="CBS_UNCHECKEDPRESSED" type="Integer" file="ATXPVS.pas" line="281">
    <value>
      $3
    </value>
  </const>
  <const name="CBS_UNCHECKEDDISABLED" type="Integer" file="ATXPVS.pas" line="283">
    <value>
      $4
    </value>
  </const>
  <const name="CBS_CHECKEDNORMAL" type="Integer" file="ATXPVS.pas" line="285">
    <value>
      $5
    </value>
  </const>
  <const name="CBS_CHECKEDHOT" type="Integer" file="ATXPVS.pas" line="287">
    <value>
      $6
    </value>
  </const>
  <const name="CBS_CHECKEDPRESSED" type="Integer" file="ATXPVS.pas" line="289">
    <value>
      $7
    </value>
  </const>
  <const name="CBS_CHECKEDDISABLED" type="Integer" file="ATXPVS.pas" line="291">
    <value>
      $8
    </value>
  </const>
  <const name="CBS_MIXEDNORMAL" type="Integer" file="ATXPVS.pas" line="293">
    <value>
      $9
    </value>
  </const>
  <const name="CBS_MIXEDHOT" type="Integer" file="ATXPVS.pas" line="295">
    <value>
      $A
    </value>
  </const>
  <const name="CBS_MIXEDPRESSED" type="Integer" file="ATXPVS.pas" line="297">
    <value>
      $B
    </value>
  </const>
  <const name="CBS_MIXEDDISABLED" type="Integer" file="ATXPVS.pas" line="299">
    <value>
      $C
    </value>
  </const>
  <const name="GBS_NORMAL" type="Integer" file="ATXPVS.pas" line="302">
    <value>
      $1
    </value>
  </const>
  <const name="GBS_DISABLED" type="Integer" file="ATXPVS.pas" line="304">
    <value>
      $2
    </value>
  </const>
  <const name="RP_GRIPPER" type="Integer" file="ATXPVS.pas" line="311">
    <value>
      $1
    </value>
  </const>
  <const name="RP_GRIPPERVERT" type="Integer" file="ATXPVS.pas" line="313">
    <value>
      $2
    </value>
  </const>
  <const name="RP_BAND" type="Integer" file="ATXPVS.pas" line="315">
    <value>
      $3
    </value>
  </const>
  <const name="RP_CHEVRON" type="Integer" file="ATXPVS.pas" line="317">
    <value>
      $4
    </value>
  </const>
  <const name="RP_CHEVRONVERT" type="Integer" file="ATXPVS.pas" line="319">
    <value>
      $5
    </value>
  </const>
  <const name="CHEVS_NORMAL" type="Integer" file="ATXPVS.pas" line="322">
    <value>
      $1
    </value>
  </const>
  <const name="CHEVS_HOT" type="Integer" file="ATXPVS.pas" line="324">
    <value>
      $2
    </value>
  </const>
  <const name="CHEVS_PRESSED" type="Integer" file="ATXPVS.pas" line="326">
    <value>
      $3
    </value>
  </const>
  <const name="TP_BUTTON" type="Integer" file="ATXPVS.pas" line="333">
    <value>
      $1
    </value>
  </const>
  <const name="TP_DROPDOWNBUTTON" type="Integer" file="ATXPVS.pas" line="335">
    <value>
      $2
    </value>
  </const>
  <const name="TP_SPLITBUTTON" type="Integer" file="ATXPVS.pas" line="337">
    <value>
      $3
    </value>
  </const>
  <const name="TP_SPLITBUTTONDROPDOWN" type="Integer" file="ATXPVS.pas" line="339">
    <value>
      $4
    </value>
  </const>
  <const name="TP_SEPARATOR" type="Integer" file="ATXPVS.pas" line="341">
    <value>
      $5
    </value>
  </const>
  <const name="TP_SEPARATORVERT" type="Integer" file="ATXPVS.pas" line="343">
    <value>
      $6
    </value>
  </const>
  <const name="TS_NORMAL" type="Integer" file="ATXPVS.pas" line="346">
    <value>
      $1
    </value>
  </const>
  <const name="TS_HOT" type="Integer" file="ATXPVS.pas" line="348">
    <value>
      $2
    </value>
  </const>
  <const name="TS_PRESSED" type="Integer" file="ATXPVS.pas" line="350">
    <value>
      $3
    </value>
  </const>
  <const name="TS_DISABLED" type="Integer" file="ATXPVS.pas" line="352">
    <value>
      $4
    </value>
  </const>
  <const name="TS_CHECKED" type="Integer" file="ATXPVS.pas" line="354">
    <value>
      $5
    </value>
  </const>
  <const name="TS_HOTCHECKED" type="Integer" file="ATXPVS.pas" line="356">
    <value>
      $6
    </value>
  </const>
  <const name="SP_PANE" type="Integer" file="ATXPVS.pas" line="362">
    <value>
      $1
    </value>
  </const>
  <const name="SP_GRIPPERPANE" type="Integer" file="ATXPVS.pas" line="364">
    <value>
      $2
    </value>
  </const>
  <const name="SP_GRIPPER" type="Integer" file="ATXPVS.pas" line="366">
    <value>
      $3
    </value>
  </const>
  <const name="MP_MENUITEM" type="Integer" file="ATXPVS.pas" line="373">
    <value>
      $1
    </value>
  </const>
  <const name="MP_MENUDROPDOWN" type="Integer" file="ATXPVS.pas" line="375">
    <value>
      $2
    </value>
  </const>
  <const name="MP_MENUBARITEM" type="Integer" file="ATXPVS.pas" line="377">
    <value>
      $3
    </value>
  </const>
  <const name="MP_MENUBARDROPDOWN" type="Integer" file="ATXPVS.pas" line="379">
    <value>
      $4
    </value>
  </const>
  <const name="MP_CHEVRON" type="Integer" file="ATXPVS.pas" line="381">
    <value>
      $5
    </value>
  </const>
  <const name="MP_SEPARATOR" type="Integer" file="ATXPVS.pas" line="383">
    <value>
      $6
    </value>
  </const>
  <const name="MS_NORMAL" type="Integer" file="ATXPVS.pas" line="386">
    <value>
      $1
    </value>
  </const>
  <const name="MS_SELECTED" type="Integer" file="ATXPVS.pas" line="388">
    <value>
      $2
    </value>
  </const>
  <const name="MS_DEMOTED" type="Integer" file="ATXPVS.pas" line="390">
    <value>
      $3
    </value>
  </const>
  <const name="LVP_LISTITEM" type="Integer" file="ATXPVS.pas" line="397">
    <value>
      $1
    </value>
  </const>
  <const name="LVP_LISTGROUP" type="Integer" file="ATXPVS.pas" line="399">
    <value>
      $2
    </value>
  </const>
  <const name="LVP_LISTDETAIL" type="Integer" file="ATXPVS.pas" line="401">
    <value>
      $3
    </value>
  </const>
  <const name="LVP_LISTSORTEDDETAIL" type="Integer" file="ATXPVS.pas" line="403">
    <value>
      $4
    </value>
  </const>
  <const name="LVP_EMPTYTEXT" type="Integer" file="ATXPVS.pas" line="405">
    <value>
      $5
    </value>
  </const>
  <const name="LIS_NORMAL" type="Integer" file="ATXPVS.pas" line="408">
    <value>
      $1
    </value>
  </const>
  <const name="LIS_HOT" type="Integer" file="ATXPVS.pas" line="410">
    <value>
      $2
    </value>
  </const>
  <const name="LIS_SELECTED" type="Integer" file="ATXPVS.pas" line="412">
    <value>
      $3
    </value>
  </const>
  <const name="LIS_DISABLED" type="Integer" file="ATXPVS.pas" line="414">
    <value>
      $4
    </value>
  </const>
  <const name="LIS_SELECTEDNOTFOCUS" type="Integer" file="ATXPVS.pas" line="416">
    <value>
      $5
    </value>
  </const>
  <const name="HP_HEADERITEM" type="Integer" file="ATXPVS.pas" line="422">
    <value>
      $1
    </value>
  </const>
  <const name="HP_HEADERITEMLEFT" type="Integer" file="ATXPVS.pas" line="424">
    <value>
      $2
    </value>
  </const>
  <const name="HP_HEADERITEMRIGHT" type="Integer" file="ATXPVS.pas" line="426">
    <value>
      $3
    </value>
  </const>
  <const name="HP_HEADERSORTARROW" type="Integer" file="ATXPVS.pas" line="428">
    <value>
      $4
    </value>
  </const>
  <const name="HIS_NORMAL" type="Integer" file="ATXPVS.pas" line="431">
    <value>
      $1
    </value>
  </const>
  <const name="HIS_HOT" type="Integer" file="ATXPVS.pas" line="433">
    <value>
      $2
    </value>
  </const>
  <const name="HIS_PRESSED" type="Integer" file="ATXPVS.pas" line="435">
    <value>
      $3
    </value>
  </const>
  <const name="HILS_NORMAL" type="Integer" file="ATXPVS.pas" line="438">
    <value>
      $1
    </value>
  </const>
  <const name="HILS_HOT" type="Integer" file="ATXPVS.pas" line="440">
    <value>
      $2
    </value>
  </const>
  <const name="HILS_PRESSED" type="Integer" file="ATXPVS.pas" line="442">
    <value>
      $3
    </value>
  </const>
  <const name="HIRS_NORMAL" type="Integer" file="ATXPVS.pas" line="445">
    <value>
      $1
    </value>
  </const>
  <const name="HIRS_HOT" type="Integer" file="ATXPVS.pas" line="447">
    <value>
      $2
    </value>
  </const>
  <const name="HIRS_PRESSED" type="Integer" file="ATXPVS.pas" line="449">
    <value>
      $3
    </value>
  </const>
  <const name="HSAS_SORTEDUP" type="Integer" file="ATXPVS.pas" line="452">
    <value>
      $1
    </value>
  </const>
  <const name="HSAS_SORTEDDOWN" type="Integer" file="ATXPVS.pas" line="454">
    <value>
      $2
    </value>
  </const>
  <const name="PP_BAR" type="Integer" file="ATXPVS.pas" line="460">
    <value>
      $1
    </value>
  </const>
  <const name="PP_BARVERT" type="Integer" file="ATXPVS.pas" line="462">
    <value>
      $2
    </value>
  </const>
  <const name="PP_CHUNK" type="Integer" file="ATXPVS.pas" line="464">
    <value>
      $3
    </value>
  </const>
  <const name="PP_CHUNKVERT" type="Integer" file="ATXPVS.pas" line="466">
    <value>
      $4
    </value>
  </const>
  <const name="TABP_TABITEM" type="Integer" file="ATXPVS.pas" line="473">
    <value>
      $1
    </value>
  </const>
  <const name="TABP_TABITEMLEFTEDGE" type="Integer" file="ATXPVS.pas" line="475">
    <value>
      $2
    </value>
  </const>
  <const name="TABP_TABITEMRIGHTEDGE" type="Integer" file="ATXPVS.pas" line="477">
    <value>
      $3
    </value>
  </const>
  <const name="TABP_TABITEMBOTHEDGE" type="Integer" file="ATXPVS.pas" line="479">
    <value>
      $4
    </value>
  </const>
  <const name="TABP_TOPTABITEM" type="Integer" file="ATXPVS.pas" line="481">
    <value>
      $5
    </value>
  </const>
  <const name="TABP_TOPTABITEMLEFTEDGE" type="Integer" file="ATXPVS.pas" line="483">
    <value>
      $6
    </value>
  </const>
  <const name="TABP_TOPTABITEMRIGHTEDGE" type="Integer" file="ATXPVS.pas" line="485">
    <value>
      $7
    </value>
  </const>
  <const name="TABP_TOPTABITEMBOTHEDGE" type="Integer" file="ATXPVS.pas" line="487">
    <value>
      $8
    </value>
  </const>
  <const name="TABP_PANE" type="Integer" file="ATXPVS.pas" line="489">
    <value>
      $9
    </value>
  </const>
  <const name="TABP_BODY" type="Integer" file="ATXPVS.pas" line="491">
    <value>
      $A
    </value>
  </const>
  <const name="TIS_NORMAL" type="Integer" file="ATXPVS.pas" line="494">
    <value>
      $1
    </value>
  </const>
  <const name="TIS_HOT" type="Integer" file="ATXPVS.pas" line="496">
    <value>
      $2
    </value>
  </const>
  <const name="TIS_SELECTED" type="Integer" file="ATXPVS.pas" line="498">
    <value>
      $3
    </value>
  </const>
  <const name="TIS_DISABLED" type="Integer" file="ATXPVS.pas" line="500">
    <value>
      $4
    </value>
  </const>
  <const name="TIS_FOCUSED" type="Integer" file="ATXPVS.pas" line="502">
    <value>
      $5
    </value>
  </const>
  <const name="TILES_NORMAL" type="Integer" file="ATXPVS.pas" line="505">
    <value>
      $1
    </value>
  </const>
  <const name="TILES_HOT" type="Integer" file="ATXPVS.pas" line="507">
    <value>
      $2
    </value>
  </const>
  <const name="TILES_SELECTED" type="Integer" file="ATXPVS.pas" line="509">
    <value>
      $3
    </value>
  </const>
  <const name="TILES_DISABLED" type="Integer" file="ATXPVS.pas" line="511">
    <value>
      $4
    </value>
  </const>
  <const name="TILES_FOCUSED" type="Integer" file="ATXPVS.pas" line="513">
    <value>
      $5
    </value>
  </const>
  <const name="TIRES_NORMAL" type="Integer" file="ATXPVS.pas" line="516">
    <value>
      $1
    </value>
  </const>
  <const name="TIRES_HOT" type="Integer" file="ATXPVS.pas" line="518">
    <value>
      $2
    </value>
  </const>
  <const name="TIRES_SELECTED" type="Integer" file="ATXPVS.pas" line="520">
    <value>
      $3
    </value>
  </const>
  <const name="TIRES_DISABLED" type="Integer" file="ATXPVS.pas" line="522">
    <value>
      $4
    </value>
  </const>
  <const name="TIRES_FOCUSED" type="Integer" file="ATXPVS.pas" line="524">
    <value>
      $5
    </value>
  </const>
  <const name="TIBES_NORMAL" type="Integer" file="ATXPVS.pas" line="527">
    <value>
      $1
    </value>
  </const>
  <const name="TIBES_HOT" type="Integer" file="ATXPVS.pas" line="529">
    <value>
      $2
    </value>
  </const>
  <const name="TIBES_SELECTED" type="Integer" file="ATXPVS.pas" line="531">
    <value>
      $3
    </value>
  </const>
  <const name="TIBES_DISABLED" type="Integer" file="ATXPVS.pas" line="533">
    <value>
      $4
    </value>
  </const>
  <const name="TIBES_FOCUSED" type="Integer" file="ATXPVS.pas" line="535">
    <value>
      $5
    </value>
  </const>
  <const name="TTIS_NORMAL" type="Integer" file="ATXPVS.pas" line="538">
    <value>
      $1
    </value>
  </const>
  <const name="TTIS_HOT" type="Integer" file="ATXPVS.pas" line="540">
    <value>
      $2
    </value>
  </const>
  <const name="TTIS_SELECTED" type="Integer" file="ATXPVS.pas" line="542">
    <value>
      $3
    </value>
  </const>
  <const name="TTIS_DISABLED" type="Integer" file="ATXPVS.pas" line="544">
    <value>
      $4
    </value>
  </const>
  <const name="TTIS_FOCUSED" type="Integer" file="ATXPVS.pas" line="546">
    <value>
      $5
    </value>
  </const>
  <const name="TTILES_NORMAL" type="Integer" file="ATXPVS.pas" line="549">
    <value>
      $1
    </value>
  </const>
  <const name="TTILES_HOT" type="Integer" file="ATXPVS.pas" line="551">
    <value>
      $2
    </value>
  </const>
  <const name="TTILES_SELECTED" type="Integer" file="ATXPVS.pas" line="553">
    <value>
      $3
    </value>
  </const>
  <const name="TTILES_DISABLED" type="Integer" file="ATXPVS.pas" line="555">
    <value>
      $4
    </value>
  </const>
  <const name="TTILES_FOCUSED" type="Integer" file="ATXPVS.pas" line="557">
    <value>
      $5
    </value>
  </const>
  <const name="TTIRES_NORMAL" type="Integer" file="ATXPVS.pas" line="560">
    <value>
      $1
    </value>
  </const>
  <const name="TTIRES_HOT" type="Integer" file="ATXPVS.pas" line="562">
    <value>
      $2
    </value>
  </const>
  <const name="TTIRES_SELECTED" type="Integer" file="ATXPVS.pas" line="564">
    <value>
      $3
    </value>
  </const>
  <const name="TTIRES_DISABLED" type="Integer" file="ATXPVS.pas" line="566">
    <value>
      $4
    </value>
  </const>
  <const name="TTIRES_FOCUSED" type="Integer" file="ATXPVS.pas" line="568">
    <value>
      $5
    </value>
  </const>
  <const name="TTIBES_NORMAL" type="Integer" file="ATXPVS.pas" line="571">
    <value>
      $1
    </value>
  </const>
  <const name="TTIBES_HOT" type="Integer" file="ATXPVS.pas" line="573">
    <value>
      $2
    </value>
  </const>
  <const name="TTIBES_SELECTED" type="Integer" file="ATXPVS.pas" line="575">
    <value>
      $3
    </value>
  </const>
  <const name="TTIBES_DISABLED" type="Integer" file="ATXPVS.pas" line="577">
    <value>
      $4
    </value>
  </const>
  <const name="TTIBES_FOCUSED" type="Integer" file="ATXPVS.pas" line="579">
    <value>
      $5
    </value>
  </const>
  <const name="TKP_TRACK" type="Integer" file="ATXPVS.pas" line="586">
    <value>
      $1
    </value>
  </const>
  <const name="TKP_TRACKVERT" type="Integer" file="ATXPVS.pas" line="588">
    <value>
      $2
    </value>
  </const>
  <const name="TKP_THUMB" type="Integer" file="ATXPVS.pas" line="590">
    <value>
      $3
    </value>
  </const>
  <const name="TKP_THUMBBOTTOM" type="Integer" file="ATXPVS.pas" line="592">
    <value>
      $4
    </value>
  </const>
  <const name="TKP_THUMBTOP" type="Integer" file="ATXPVS.pas" line="594">
    <value>
      $5
    </value>
  </const>
  <const name="TKP_THUMBVERT" type="Integer" file="ATXPVS.pas" line="596">
    <value>
      $6
    </value>
  </const>
  <const name="TKP_THUMBLEFT" type="Integer" file="ATXPVS.pas" line="598">
    <value>
      $7
    </value>
  </const>
  <const name="TKP_THUMBRIGHT" type="Integer" file="ATXPVS.pas" line="600">
    <value>
      $8
    </value>
  </const>
  <const name="TKP_TICS" type="Integer" file="ATXPVS.pas" line="602">
    <value>
      $9
    </value>
  </const>
  <const name="TKP_TICSVERT" type="Integer" file="ATXPVS.pas" line="604">
    <value>
      $A
    </value>
  </const>
  <const name="TKS_NORMAL" type="Integer" file="ATXPVS.pas" line="607">
    <value>
      $1
    </value>
  </const>
  <const name="TRS_NORMAL" type="Integer" file="ATXPVS.pas" line="609">
    <value>
      $1
    </value>
  </const>
  <const name="TRVS_NORMAL" type="Integer" file="ATXPVS.pas" line="611">
    <value>
      $1
    </value>
  </const>
  <const name="TUS_NORMAL" type="Integer" file="ATXPVS.pas" line="614">
    <value>
      $1
    </value>
  </const>
  <const name="TUS_HOT" type="Integer" file="ATXPVS.pas" line="616">
    <value>
      $2
    </value>
  </const>
  <const name="TUS_PRESSED" type="Integer" file="ATXPVS.pas" line="618">
    <value>
      $3
    </value>
  </const>
  <const name="TUS_FOCUSED" type="Integer" file="ATXPVS.pas" line="620">
    <value>
      $4
    </value>
  </const>
  <const name="TUS_DISABLED" type="Integer" file="ATXPVS.pas" line="622">
    <value>
      $5
    </value>
  </const>
  <const name="TUBS_NORMAL" type="Integer" file="ATXPVS.pas" line="625">
    <value>
      $1
    </value>
  </const>
  <const name="TUBS_HOT" type="Integer" file="ATXPVS.pas" line="627">
    <value>
      $2
    </value>
  </const>
  <const name="TUBS_PRESSED" type="Integer" file="ATXPVS.pas" line="629">
    <value>
      $3
    </value>
  </const>
  <const name="TUBS_FOCUSED" type="Integer" file="ATXPVS.pas" line="631">
    <value>
      $4
    </value>
  </const>
  <const name="TUBS_DISABLED" type="Integer" file="ATXPVS.pas" line="633">
    <value>
      $5
    </value>
  </const>
  <const name="TUTS_NORMAL" type="Integer" file="ATXPVS.pas" line="636">
    <value>
      $1
    </value>
  </const>
  <const name="TUTS_HOT" type="Integer" file="ATXPVS.pas" line="638">
    <value>
      $2
    </value>
  </const>
  <const name="TUTS_PRESSED" type="Integer" file="ATXPVS.pas" line="640">
    <value>
      $3
    </value>
  </const>
  <const name="TUTS_FOCUSED" type="Integer" file="ATXPVS.pas" line="642">
    <value>
      $4
    </value>
  </const>
  <const name="TUTS_DISABLED" type="Integer" file="ATXPVS.pas" line="644">
    <value>
      $5
    </value>
  </const>
  <const name="TUVS_NORMAL" type="Integer" file="ATXPVS.pas" line="647">
    <value>
      $1
    </value>
  </const>
  <const name="TUVS_HOT" type="Integer" file="ATXPVS.pas" line="649">
    <value>
      $2
    </value>
  </const>
  <const name="TUVS_PRESSED" type="Integer" file="ATXPVS.pas" line="651">
    <value>
      $3
    </value>
  </const>
  <const name="TUVS_FOCUSED" type="Integer" file="ATXPVS.pas" line="653">
    <value>
      $4
    </value>
  </const>
  <const name="TUVS_DISABLED" type="Integer" file="ATXPVS.pas" line="655">
    <value>
      $5
    </value>
  </const>
  <const name="TUVLS_NORMAL" type="Integer" file="ATXPVS.pas" line="658">
    <value>
      $1
    </value>
  </const>
  <const name="TUVLS_HOT" type="Integer" file="ATXPVS.pas" line="660">
    <value>
      $2
    </value>
  </const>
  <const name="TUVLS_PRESSED" type="Integer" file="ATXPVS.pas" line="662">
    <value>
      $3
    </value>
  </const>
  <const name="TUVLS_FOCUSED" type="Integer" file="ATXPVS.pas" line="664">
    <value>
      $4
    </value>
  </const>
  <const name="TUVLS_DISABLED" type="Integer" file="ATXPVS.pas" line="666">
    <value>
      $5
    </value>
  </const>
  <const name="TUVRS_NORMAL" type="Integer" file="ATXPVS.pas" line="669">
    <value>
      $1
    </value>
  </const>
  <const name="TUVRS_HOT" type="Integer" file="ATXPVS.pas" line="671">
    <value>
      $2
    </value>
  </const>
  <const name="TUVRS_PRESSED" type="Integer" file="ATXPVS.pas" line="673">
    <value>
      $3
    </value>
  </const>
  <const name="TUVRS_FOCUSED" type="Integer" file="ATXPVS.pas" line="675">
    <value>
      $4
    </value>
  </const>
  <const name="TUVRS_DISABLED" type="Integer" file="ATXPVS.pas" line="677">
    <value>
      $5
    </value>
  </const>
  <const name="TSS_NORMAL" type="Integer" file="ATXPVS.pas" line="680">
    <value>
      $1
    </value>
  </const>
  <const name="TSVS_NORMAL" type="Integer" file="ATXPVS.pas" line="683">
    <value>
      $1
    </value>
  </const>
  <const name="TTP_STANDARD" type="Integer" file="ATXPVS.pas" line="690">
    <value>
      $1
    </value>
  </const>
  <const name="TTP_STANDARDTITLE" type="Integer" file="ATXPVS.pas" line="692">
    <value>
      $2
    </value>
  </const>
  <const name="TTP_BALLOON" type="Integer" file="ATXPVS.pas" line="694">
    <value>
      $3
    </value>
  </const>
  <const name="TTP_BALLOONTITLE" type="Integer" file="ATXPVS.pas" line="696">
    <value>
      $4
    </value>
  </const>
  <const name="TTP_CLOSE" type="Integer" file="ATXPVS.pas" line="698">
    <value>
      $5
    </value>
  </const>
  <const name="TTCS_NORMAL" type="Integer" file="ATXPVS.pas" line="701">
    <value>
      $1
    </value>
  </const>
  <const name="TTCS_HOT" type="Integer" file="ATXPVS.pas" line="703">
    <value>
      $2
    </value>
  </const>
  <const name="TTCS_PRESSED" type="Integer" file="ATXPVS.pas" line="705">
    <value>
      $3
    </value>
  </const>
  <const name="TTSS_NORMAL" type="Integer" file="ATXPVS.pas" line="708">
    <value>
      $1
    </value>
  </const>
  <const name="TTSS_LINK" type="Integer" file="ATXPVS.pas" line="710">
    <value>
      $2
    </value>
  </const>
  <const name="TTBS_NORMAL" type="Integer" file="ATXPVS.pas" line="713">
    <value>
      $1
    </value>
  </const>
  <const name="TTBS_LINK" type="Integer" file="ATXPVS.pas" line="715">
    <value>
      $2
    </value>
  </const>
  <const name="TVP_TREEITEM" type="Integer" file="ATXPVS.pas" line="722">
    <value>
      $1
    </value>
  </const>
  <const name="TVP_GLYPH" type="Integer" file="ATXPVS.pas" line="724">
    <value>
      $2
    </value>
  </const>
  <const name="TVP_BRANCH" type="Integer" file="ATXPVS.pas" line="726">
    <value>
      $3
    </value>
  </const>
  <const name="TREIS_NORMAL" type="Integer" file="ATXPVS.pas" line="729">
    <value>
      $1
    </value>
  </const>
  <const name="TREIS_HOT" type="Integer" file="ATXPVS.pas" line="731">
    <value>
      $2
    </value>
  </const>
  <const name="TREIS_SELECTED" type="Integer" file="ATXPVS.pas" line="733">
    <value>
      $3
    </value>
  </const>
  <const name="TREIS_DISABLED" type="Integer" file="ATXPVS.pas" line="735">
    <value>
      $4
    </value>
  </const>
  <const name="TREIS_SELECTEDNOTFOCUS" type="Integer" file="ATXPVS.pas" line="737">
    <value>
      $5
    </value>
  </const>
  <const name="GLPS_CLOSED" type="Integer" file="ATXPVS.pas" line="740">
    <value>
      $1
    </value>
  </const>
  <const name="GLPS_OPENED" type="Integer" file="ATXPVS.pas" line="742">
    <value>
      $2
    </value>
  </const>
  <const name="SPNP_UP" type="Integer" file="ATXPVS.pas" line="749">
    <value>
      $1
    </value>
  </const>
  <const name="SPNP_DOWN" type="Integer" file="ATXPVS.pas" line="751">
    <value>
      $2
    </value>
  </const>
  <const name="SPNP_UPHORZ" type="Integer" file="ATXPVS.pas" line="753">
    <value>
      $3
    </value>
  </const>
  <const name="SPNP_DOWNHORZ" type="Integer" file="ATXPVS.pas" line="755">
    <value>
      $4
    </value>
  </const>
  <const name="UPS_NORMAL" type="Integer" file="ATXPVS.pas" line="758">
    <value>
      $1
    </value>
  </const>
  <const name="UPS_HOT" type="Integer" file="ATXPVS.pas" line="760">
    <value>
      $2
    </value>
  </const>
  <const name="UPS_PRESSED" type="Integer" file="ATXPVS.pas" line="762">
    <value>
      $3
    </value>
  </const>
  <const name="UPS_DISABLED" type="Integer" file="ATXPVS.pas" line="764">
    <value>
      $4
    </value>
  </const>
  <const name="DNS_NORMAL" type="Integer" file="ATXPVS.pas" line="767">
    <value>
      $1
    </value>
  </const>
  <const name="DNS_HOT" type="Integer" file="ATXPVS.pas" line="769">
    <value>
      $2
    </value>
  </const>
  <const name="DNS_PRESSED" type="Integer" file="ATXPVS.pas" line="771">
    <value>
      $3
    </value>
  </const>
  <const name="DNS_DISABLED" type="Integer" file="ATXPVS.pas" line="773">
    <value>
      $4
    </value>
  </const>
  <const name="UPHZS_NORMAL" type="Integer" file="ATXPVS.pas" line="776">
    <value>
      $1
    </value>
  </const>
  <const name="UPHZS_HOT" type="Integer" file="ATXPVS.pas" line="778">
    <value>
      $2
    </value>
  </const>
  <const name="UPHZS_PRESSED" type="Integer" file="ATXPVS.pas" line="780">
    <value>
      $3
    </value>
  </const>
  <const name="UPHZS_DISABLED" type="Integer" file="ATXPVS.pas" line="782">
    <value>
      $4
    </value>
  </const>
  <const name="DNHZS_NORMAL" type="Integer" file="ATXPVS.pas" line="785">
    <value>
      $1
    </value>
  </const>
  <const name="DNHZS_HOT" type="Integer" file="ATXPVS.pas" line="787">
    <value>
      $2
    </value>
  </const>
  <const name="DNHZS_PRESSED" type="Integer" file="ATXPVS.pas" line="789">
    <value>
      $3
    </value>
  </const>
  <const name="DNHZS_DISABLED" type="Integer" file="ATXPVS.pas" line="791">
    <value>
      $4
    </value>
  </const>
  <const name="PGRP_UP" type="Integer" file="ATXPVS.pas" line="798">
    <value>
      $1
    </value>
  </const>
  <const name="PGRP_DOWN" type="Integer" file="ATXPVS.pas" line="800">
    <value>
      $2
    </value>
  </const>
  <const name="PGRP_UPHORZ" type="Integer" file="ATXPVS.pas" line="802">
    <value>
      $3
    </value>
  </const>
  <const name="PGRP_DOWNHORZ" type="Integer" file="ATXPVS.pas" line="804">
    <value>
      $4
    </value>
  </const>
  <const name="SBP_ARROWBTN" type="Integer" file="ATXPVS.pas" line="813">
    <value>
      $1
    </value>
  </const>
  <const name="SBP_THUMBBTNHORZ" type="Integer" file="ATXPVS.pas" line="815">
    <value>
      $2
    </value>
  </const>
  <const name="SBP_THUMBBTNVERT" type="Integer" file="ATXPVS.pas" line="817">
    <value>
      $3
    </value>
  </const>
  <const name="SBP_LOWERTRACKHORZ" type="Integer" file="ATXPVS.pas" line="819">
    <value>
      $4
    </value>
  </const>
  <const name="SBP_UPPERTRACKHORZ" type="Integer" file="ATXPVS.pas" line="821">
    <value>
      $5
    </value>
  </const>
  <const name="SBP_LOWERTRACKVERT" type="Integer" file="ATXPVS.pas" line="823">
    <value>
      $6
    </value>
  </const>
  <const name="SBP_UPPERTRACKVERT" type="Integer" file="ATXPVS.pas" line="825">
    <value>
      $7
    </value>
  </const>
  <const name="SBP_GRIPPERHORZ" type="Integer" file="ATXPVS.pas" line="827">
    <value>
      $8
    </value>
  </const>
  <const name="SBP_GRIPPERVERT" type="Integer" file="ATXPVS.pas" line="829">
    <value>
      $9
    </value>
  </const>
  <const name="SBP_SIZEBOX" type="Integer" file="ATXPVS.pas" line="831">
    <value>
      $A
    </value>
  </const>
  <const name="ABS_UPNORMAL" type="Integer" file="ATXPVS.pas" line="834">
    <value>
      $1
    </value>
  </const>
  <const name="ABS_UPHOT" type="Integer" file="ATXPVS.pas" line="836">
    <value>
      $2
    </value>
  </const>
  <const name="ABS_UPPRESSED" type="Integer" file="ATXPVS.pas" line="838">
    <value>
      $3
    </value>
  </const>
  <const name="ABS_UPDISABLED" type="Integer" file="ATXPVS.pas" line="840">
    <value>
      $4
    </value>
  </const>
  <const name="ABS_DOWNNORMAL" type="Integer" file="ATXPVS.pas" line="842">
    <value>
      $5
    </value>
  </const>
  <const name="ABS_DOWNHOT" type="Integer" file="ATXPVS.pas" line="844">
    <value>
      $6
    </value>
  </const>
  <const name="ABS_DOWNPRESSED" type="Integer" file="ATXPVS.pas" line="846">
    <value>
      $7
    </value>
  </const>
  <const name="ABS_DOWNDISABLED" type="Integer" file="ATXPVS.pas" line="848">
    <value>
      $8
    </value>
  </const>
  <const name="ABS_LEFTNORMAL" type="Integer" file="ATXPVS.pas" line="850">
    <value>
      $9
    </value>
  </const>
  <const name="ABS_LEFTHOT" type="Integer" file="ATXPVS.pas" line="852">
    <value>
      $A
    </value>
  </const>
  <const name="ABS_LEFTPRESSED" type="Integer" file="ATXPVS.pas" line="854">
    <value>
      $B
    </value>
  </const>
  <const name="ABS_LEFTDISABLED" type="Integer" file="ATXPVS.pas" line="856">
    <value>
      $C
    </value>
  </const>
  <const name="ABS_RIGHTNORMAL" type="Integer" file="ATXPVS.pas" line="858">
    <value>
      $D
    </value>
  </const>
  <const name="ABS_RIGHTHOT" type="Integer" file="ATXPVS.pas" line="860">
    <value>
      $E
    </value>
  </const>
  <const name="ABS_RIGHTPRESSED" type="Integer" file="ATXPVS.pas" line="862">
    <value>
      $F
    </value>
  </const>
  <const name="ABS_RIGHTDISABLED" type="Integer" file="ATXPVS.pas" line="864">
    <value>
      $10
    </value>
  </const>
  <const name="SCRBS_NORMAL" type="Integer" file="ATXPVS.pas" line="867">
    <value>
      $1
    </value>
  </const>
  <const name="SCRBS_HOT" type="Integer" file="ATXPVS.pas" line="869">
    <value>
      $2
    </value>
  </const>
  <const name="SCRBS_PRESSED" type="Integer" file="ATXPVS.pas" line="871">
    <value>
      $3
    </value>
  </const>
  <const name="SCRBS_DISABLED" type="Integer" file="ATXPVS.pas" line="873">
    <value>
      $4
    </value>
  </const>
  <const name="SZB_RIGHTALIGN" type="Integer" file="ATXPVS.pas" line="876">
    <value>
      $1
    </value>
  </const>
  <const name="SZB_LEFTALIGN" type="Integer" file="ATXPVS.pas" line="878">
    <value>
      $2
    </value>
  </const>
  <const name="EP_EDITTEXT" type="Integer" file="ATXPVS.pas" line="884">
    <value>
      $1
    </value>
  </const>
  <const name="EP_CARET" type="Integer" file="ATXPVS.pas" line="886">
    <value>
      $2
    </value>
  </const>
  <const name="ETS_NORMAL" type="Integer" file="ATXPVS.pas" line="889">
    <value>
      $1
    </value>
  </const>
  <const name="ETS_HOT" type="Integer" file="ATXPVS.pas" line="891">
    <value>
      $2
    </value>
  </const>
  <const name="ETS_SELECTED" type="Integer" file="ATXPVS.pas" line="893">
    <value>
      $3
    </value>
  </const>
  <const name="ETS_DISABLED" type="Integer" file="ATXPVS.pas" line="895">
    <value>
      $4
    </value>
  </const>
  <const name="ETS_FOCUSED" type="Integer" file="ATXPVS.pas" line="897">
    <value>
      $5
    </value>
  </const>
  <const name="ETS_READONLY" type="Integer" file="ATXPVS.pas" line="899">
    <value>
      $6
    </value>
  </const>
  <const name="ETS_ASSIST" type="Integer" file="ATXPVS.pas" line="901">
    <value>
      $7
    </value>
  </const>
  <const name="CP_DROPDOWNBUTTON" type="Integer" file="ATXPVS.pas" line="908">
    <value>
      $1
    </value>
  </const>
  <const name="CBXS_NORMAL" type="Integer" file="ATXPVS.pas" line="911">
    <value>
      $1
    </value>
  </const>
  <const name="CBXS_HOT" type="Integer" file="ATXPVS.pas" line="913">
    <value>
      $2
    </value>
  </const>
  <const name="CBXS_PRESSED" type="Integer" file="ATXPVS.pas" line="915">
    <value>
      $3
    </value>
  </const>
  <const name="CBXS_DISABLED" type="Integer" file="ATXPVS.pas" line="917">
    <value>
      $4
    </value>
  </const>
  <const name="CLP_TIME" type="Integer" file="ATXPVS.pas" line="924">
    <value>
      $1
    </value>
  </const>
  <const name="CLS_NORMAL" type="Integer" file="ATXPVS.pas" line="926">
    <value>
      $1
    </value>
  </const>
  <const name="TNP_BACKGROUND" type="Integer" file="ATXPVS.pas" line="933">
    <value>
      $1
    </value>
  </const>
  <const name="TNP_ANIMBACKGROUND" type="Integer" file="ATXPVS.pas" line="935">
    <value>
      $2
    </value>
  </const>
  <const name="TBP_BACKGROUNDBOTTOM" type="Integer" file="ATXPVS.pas" line="942">
    <value>
      $1
    </value>
  </const>
  <const name="TBP_BACKGROUNDRIGHT" type="Integer" file="ATXPVS.pas" line="944">
    <value>
      $2
    </value>
  </const>
  <const name="TBP_BACKGROUNDTOP" type="Integer" file="ATXPVS.pas" line="946">
    <value>
      $3
    </value>
  </const>
  <const name="TBP_BACKGROUNDLEFT" type="Integer" file="ATXPVS.pas" line="948">
    <value>
      $4
    </value>
  </const>
  <const name="TBP_SIZINGBARBOTTOM" type="Integer" file="ATXPVS.pas" line="950">
    <value>
      $5
    </value>
  </const>
  <const name="TBP_SIZINGBARRIGHT" type="Integer" file="ATXPVS.pas" line="952">
    <value>
      $6
    </value>
  </const>
  <const name="TBP_SIZINGBARTOP" type="Integer" file="ATXPVS.pas" line="954">
    <value>
      $7
    </value>
  </const>
  <const name="TBP_SIZINGBARLEFT" type="Integer" file="ATXPVS.pas" line="956">
    <value>
      $8
    </value>
  </const>
  <const name="TDP_GROUPCOUNT" type="Integer" file="ATXPVS.pas" line="963">
    <value>
      $1
    </value>
  </const>
  <const name="TDP_FLASHBUTTON" type="Integer" file="ATXPVS.pas" line="965">
    <value>
      $2
    </value>
  </const>
  <const name="TDP_FLASHBUTTONGROUPMENU" type="Integer" file="ATXPVS.pas" line="967">
    <value>
      $3
    </value>
  </const>
  <const name="SPP_USERPANE" type="Integer" file="ATXPVS.pas" line="974">
    <value>
      $1
    </value>
  </const>
  <const name="SPP_MOREPROGRAMS" type="Integer" file="ATXPVS.pas" line="976">
    <value>
      $2
    </value>
  </const>
  <const name="SPP_MOREPROGRAMSARROW" type="Integer" file="ATXPVS.pas" line="978">
    <value>
      $3
    </value>
  </const>
  <const name="SPP_PROGLIST" type="Integer" file="ATXPVS.pas" line="980">
    <value>
      $4
    </value>
  </const>
  <const name="SPP_PROGLISTSEPARATOR" type="Integer" file="ATXPVS.pas" line="982">
    <value>
      $5
    </value>
  </const>
  <const name="SPP_PLACESLIST" type="Integer" file="ATXPVS.pas" line="984">
    <value>
      $6
    </value>
  </const>
  <const name="SPP_PLACESLISTSEPARATOR" type="Integer" file="ATXPVS.pas" line="986">
    <value>
      $7
    </value>
  </const>
  <const name="SPP_LOGOFF" type="Integer" file="ATXPVS.pas" line="988">
    <value>
      $8
    </value>
  </const>
  <const name="SPP_LOGOFFBUTTONS" type="Integer" file="ATXPVS.pas" line="990">
    <value>
      $9
    </value>
  </const>
  <const name="SPP_USERPICTURE" type="Integer" file="ATXPVS.pas" line="992">
    <value>
      $A
    </value>
  </const>
  <const name="SPP_PREVIEW" type="Integer" file="ATXPVS.pas" line="994">
    <value>
      $B
    </value>
  </const>
  <const name="SPS_NORMAL" type="Integer" file="ATXPVS.pas" line="997">
    <value>
      $1
    </value>
  </const>
  <const name="SPS_HOT" type="Integer" file="ATXPVS.pas" line="999">
    <value>
      $2
    </value>
  </const>
  <const name="SPS_PRESSED" type="Integer" file="ATXPVS.pas" line="1001">
    <value>
      $3
    </value>
  </const>
  <const name="SPLS_NORMAL" type="Integer" file="ATXPVS.pas" line="1004">
    <value>
      $1
    </value>
  </const>
  <const name="SPLS_HOT" type="Integer" file="ATXPVS.pas" line="1006">
    <value>
      $2
    </value>
  </const>
  <const name="SPLS_PRESSED" type="Integer" file="ATXPVS.pas" line="1008">
    <value>
      $3
    </value>
  </const>
  <const name="EBP_HEADERBACKGROUND" type="Integer" file="ATXPVS.pas" line="1015">
    <value>
      $1
    </value>
  </const>
  <const name="EBP_HEADERCLOSE" type="Integer" file="ATXPVS.pas" line="1017">
    <value>
      $2
    </value>
  </const>
  <const name="EBP_HEADERPIN" type="Integer" file="ATXPVS.pas" line="1019">
    <value>
      $3
    </value>
  </const>
  <const name="EBP_IEBARMENU" type="Integer" file="ATXPVS.pas" line="1021">
    <value>
      $4
    </value>
  </const>
  <const name="EBP_NORMALGROUPBACKGROUND" type="Integer" file="ATXPVS.pas" line="1023">
    <value>
      $5
    </value>
  </const>
  <const name="EBP_NORMALGROUPCOLLAPSE" type="Integer" file="ATXPVS.pas" line="1025">
    <value>
      $6
    </value>
  </const>
  <const name="EBP_NORMALGROUPEXPAND" type="Integer" file="ATXPVS.pas" line="1027">
    <value>
      $7
    </value>
  </const>
  <const name="EBP_NORMALGROUPHEAD" type="Integer" file="ATXPVS.pas" line="1029">
    <value>
      $8
    </value>
  </const>
  <const name="EBP_SPECIALGROUPBACKGROUND" type="Integer" file="ATXPVS.pas" line="1031">
    <value>
      $9
    </value>
  </const>
  <const name="EBP_SPECIALGROUPCOLLAPSE" type="Integer" file="ATXPVS.pas" line="1033">
    <value>
      $A
    </value>
  </const>
  <const name="EBP_SPECIALGROUPEXPAND" type="Integer" file="ATXPVS.pas" line="1035">
    <value>
      $B
    </value>
  </const>
  <const name="EBP_SPECIALGROUPHEAD" type="Integer" file="ATXPVS.pas" line="1037">
    <value>
      $C
    </value>
  </const>
  <const name="EBHC_NORMAL" type="Integer" file="ATXPVS.pas" line="1040">
    <value>
      $1
    </value>
  </const>
  <const name="EBHC_HOT" type="Integer" file="ATXPVS.pas" line="1042">
    <value>
      $2
    </value>
  </const>
  <const name="EBHC_PRESSED" type="Integer" file="ATXPVS.pas" line="1044">
    <value>
      $3
    </value>
  </const>
  <const name="EBHP_NORMAL" type="Integer" file="ATXPVS.pas" line="1047">
    <value>
      $1
    </value>
  </const>
  <const name="EBHP_HOT" type="Integer" file="ATXPVS.pas" line="1049">
    <value>
      $2
    </value>
  </const>
  <const name="EBHP_PRESSED" type="Integer" file="ATXPVS.pas" line="1051">
    <value>
      $3
    </value>
  </const>
  <const name="EBHP_SELECTEDNORMAL" type="Integer" file="ATXPVS.pas" line="1053">
    <value>
      $4
    </value>
  </const>
  <const name="EBHP_SELECTEDHOT" type="Integer" file="ATXPVS.pas" line="1055">
    <value>
      $5
    </value>
  </const>
  <const name="EBHP_SELECTEDPRESSED" type="Integer" file="ATXPVS.pas" line="1057">
    <value>
      $6
    </value>
  </const>
  <const name="EBM_NORMAL" type="Integer" file="ATXPVS.pas" line="1060">
    <value>
      $1
    </value>
  </const>
  <const name="EBM_HOT" type="Integer" file="ATXPVS.pas" line="1062">
    <value>
      $2
    </value>
  </const>
  <const name="EBM_PRESSED" type="Integer" file="ATXPVS.pas" line="1064">
    <value>
      $3
    </value>
  </const>
  <const name="EBNGC_NORMAL" type="Integer" file="ATXPVS.pas" line="1067">
    <value>
      $1
    </value>
  </const>
  <const name="EBNGC_HOT" type="Integer" file="ATXPVS.pas" line="1069">
    <value>
      $2
    </value>
  </const>
  <const name="EBNGC_PRESSED" type="Integer" file="ATXPVS.pas" line="1071">
    <value>
      $3
    </value>
  </const>
  <const name="EBNGE_NORMAL" type="Integer" file="ATXPVS.pas" line="1074">
    <value>
      $1
    </value>
  </const>
  <const name="EBNGE_HOT" type="Integer" file="ATXPVS.pas" line="1076">
    <value>
      $2
    </value>
  </const>
  <const name="EBNGE_PRESSED" type="Integer" file="ATXPVS.pas" line="1078">
    <value>
      $3
    </value>
  </const>
  <const name="EBSGC_NORMAL" type="Integer" file="ATXPVS.pas" line="1081">
    <value>
      $1
    </value>
  </const>
  <const name="EBSGC_HOT" type="Integer" file="ATXPVS.pas" line="1083">
    <value>
      $2
    </value>
  </const>
  <const name="EBSGC_PRESSED" type="Integer" file="ATXPVS.pas" line="1085">
    <value>
      $3
    </value>
  </const>
  <const name="EBSGE_NORMAL" type="Integer" file="ATXPVS.pas" line="1088">
    <value>
      $1
    </value>
  </const>
  <const name="EBSGE_HOT" type="Integer" file="ATXPVS.pas" line="1090">
    <value>
      $2
    </value>
  </const>
  <const name="EBSGE_PRESSED" type="Integer" file="ATXPVS.pas" line="1092">
    <value>
      $3
    </value>
  </const>
  <const name="MDP_NEWAPPBUTTON" type="Integer" file="ATXPVS.pas" line="1098">
    <value>
      $1
    </value>
  </const>
  <const name="MDP_SEPERATOR" type="Integer" file="ATXPVS.pas" line="1100">
    <value>
      $2
    </value>
  </const>
  <const name="MDS_NORMAL" type="Integer" file="ATXPVS.pas" line="1103">
    <value>
      $1
    </value>
  </const>
  <const name="MDS_HOT" type="Integer" file="ATXPVS.pas" line="1105">
    <value>
      $2
    </value>
  </const>
  <const name="MDS_PRESSED" type="Integer" file="ATXPVS.pas" line="1107">
    <value>
      $3
    </value>
  </const>
  <const name="MDS_DISABLED" type="Integer" file="ATXPVS.pas" line="1109">
    <value>
      $4
    </value>
  </const>
  <const name="MDS_CHECKED" type="Integer" file="ATXPVS.pas" line="1111">
    <value>
      $5
    </value>
  </const>
  <const name="MDS_HOTCHECKED" type="Integer" file="ATXPVS.pas" line="1113">
    <value>
      $6
    </value>
  </const>
  <const name="DTT_GRAYED" type="Integer" file="ATXPVS.pas" line="1116">
    <value>
      $1
    </value>
  </const>
  <const name="HTTB_BACKGROUNDSEG" type="Integer" file="ATXPVS.pas" line="1119">
    <value>
      $0
    </value>
  </const>
  <const name="HTTB_FIXEDBORDER" type="Integer" file="ATXPVS.pas" line="1121">
    <value>
      $2
    </value>
  </const>
  <const name="HTTB_CAPTION" type="Integer" file="ATXPVS.pas" line="1123">
    <value>
      $4
    </value>
  </const>
  <const name="HTTB_RESIZINGBORDER_LEFT" type="Integer" file="ATXPVS.pas" line="1125">
    <value>
      $10
    </value>
  </const>
  <const name="HTTB_RESIZINGBORDER_TOP" type="Integer" file="ATXPVS.pas" line="1127">
    <value>
      $20
    </value>
  </const>
  <const name="HTTB_RESIZINGBORDER_RIGHT" type="Integer" file="ATXPVS.pas" line="1129">
    <value>
      $40
    </value>
  </const>
  <const name="HTTB_RESIZINGBORDER_BOTTOM" type="Integer" file="ATXPVS.pas" line="1131">
    <value>
      $80
    </value>
  </const>
  <const name="HTTB_RESIZINGBORDER" type="Integer" file="ATXPVS.pas" line="1133">
    <value>
      $30
    </value>
  </const>
  <const name="HTTB_SIZINGTEMPLATE" type="Integer" file="ATXPVS.pas" line="1135">
    <value>
      $100
    </value>
  </const>
  <const name="HTTB_SYSTEMSIZINGMARGINS" type="Integer" file="ATXPVS.pas" line="1137">
    <value>
      $200
    </value>
  </const>
  <const name="MAX_INTLIST_COUNT" type="Integer" file="ATXPVS.pas" line="1140">
    <value>
      $A
    </value>
  </const>
  <const name="ETDT_DISABLE" type="Integer" file="ATXPVS.pas" line="1143">
    <value>
      $1
    </value>
  </const>
  <const name="ETDT_ENABLE" type="Integer" file="ATXPVS.pas" line="1145">
    <value>
      $2
    </value>
  </const>
  <const name="ETDT_USETABTEXTURE" type="Integer" file="ATXPVS.pas" line="1147">
    <value>
      $4
    </value>
  </const>
  <const name="ETDT_ENABLETAB" type="Integer" file="ATXPVS.pas" line="1149">
    <value>
      $6
    </value>
  </const>
  <const name="STAP_ALLOW_NONCLIENT" type="Integer" file="ATXPVS.pas" line="1152">
    <value>
      $1
    </value>
  </const>
  <const name="STAP_ALLOW_CONTROLS" type="Integer" file="ATXPVS.pas" line="1155">
    <value>
      $2
    </value>
  </const>
  <const name="STAP_ALLOW_WEBCONTENT" type="Integer" file="ATXPVS.pas" line="1158">
    <value>
      $4
    </value>
  </const>
  <const name="SZ_THDOCPROP_DISPLAYNAME" type="string" file="ATXPVS.pas" line="1161">
    <value>
      DisplayName
    </value>
  </const>
  <const name="SZ_THDOCPROP_CANONICALNAME" type="string" file="ATXPVS.pas" line="1164">
    <value>
      ThemeName
    </value>
  </const>
  <const name="SZ_THDOCPROP_TOOLTIP" type="string" file="ATXPVS.pas" line="1167">
    <value>
      ToolTip
    </value>
  </const>
  <const name="SZ_THDOCPROP_AUTHOR" type="string" file="ATXPVS.pas" line="1170">
    <value>
      author
    </value>
  </const>
  <const name="GP_BORDER" type="Integer" file="ATXPVS.pas" line="1173">
    <value>
      $1
    </value>
  </const>
  <const name="GP_LINEHORZ" type="Integer" file="ATXPVS.pas" line="1175">
    <value>
      $2
    </value>
  </const>
  <const name="GP_LINEVERT" type="Integer" file="ATXPVS.pas" line="1177">
    <value>
      $3
    </value>
  </const>
  <const name="BSS_FLAT" type="Integer" file="ATXPVS.pas" line="1180">
    <value>
      $1
    </value>
  </const>
  <const name="BSS_RAISED" type="Integer" file="ATXPVS.pas" line="1182">
    <value>
      $2
    </value>
  </const>
  <const name="BSS_SUNKED" type="Integer" file="ATXPVS.pas" line="1184">
    <value>
      $4
    </value>
  </const>
  <type name="HTHEME" type="cardinal" loBound="0" hiBound="-1" file="System.pas" line="12" />
  <struct name="_MARGINS" size="16" file="ATXPVS.pas" line="1192">
    <field name="cxLeftWidth" type="Integer" visibility="public" size="4" offset="0" file="ATXPVS.pas" line="1193" />
    <field name="cxRightWidth" type="Integer" visibility="public" size="4" offset="4" file="ATXPVS.pas" line="1194" />
    <field name="cyTopHeight" type="Integer" visibility="public" size="4" offset="8" file="ATXPVS.pas" line="1195" />
    <field name="cyBottomHeight" type="Integer" visibility="public" size="4" offset="12" file="ATXPVS.pas" line="1196" />
  </struct>
  <struct name="MARGINS" alias="ATXPVS._MARGINS" size="16" file="ATXPVS.pas" line="1199">
    <field name="cxLeftWidth" type="Integer" visibility="public" size="4" offset="0" file="ATXPVS.pas" line="1193" />
    <field name="cxRightWidth" type="Integer" visibility="public" size="4" offset="4" file="ATXPVS.pas" line="1194" />
    <field name="cyTopHeight" type="Integer" visibility="public" size="4" offset="8" file="ATXPVS.pas" line="1195" />
    <field name="cyBottomHeight" type="Integer" visibility="public" size="4" offset="12" file="ATXPVS.pas" line="1196" />
  </struct>
  <pointer name="PMARGINS" type="_MARGINS" indircnt="1" file="ATXPVS.pas" line="1201" />
  <struct name="_INTLIST" size="44" file="ATXPVS.pas" line="1204">
    <field name="iValueCount" type="Integer" visibility="public" size="4" offset="0" file="ATXPVS.pas" line="1205" />
    <field name="iValues" visibility="public" size="40" offset="4" file="ATXPVS.pas" line="1206">
      <array name="iValues" visibility="public" low="0" high="9" file="ATXPVS.pas" line="1206">
        <element type="Integer" />
      </array>
    </field>
  </struct>
  <struct name="INTLIST" alias="ATXPVS._INTLIST" size="44" file="ATXPVS.pas" line="1209">
    <field name="iValueCount" type="Integer" visibility="public" size="4" offset="0" file="ATXPVS.pas" line="1205" />
    <field name="iValues" visibility="public" size="40" offset="4" file="ATXPVS.pas" line="1206">
      <array name="iValues" visibility="public" low="0" high="9" file="ATXPVS.pas" line="1206">
        <element type="Integer" />
      </array>
    </field>
  </struct>
  <pointer name="PINTLIST" type="_INTLIST" indircnt="1" file="ATXPVS.pas" line="1211" />
  <struct name="TDTBGOPTS" size="24" file="ATXPVS.pas" line="1214">
    <field name="dwSize" type="Cardinal" visibility="public" size="4" offset="0" file="ATXPVS.pas" line="1215" />
    <field name="dwFlags" type="Cardinal" visibility="public" size="4" offset="4" file="ATXPVS.pas" line="1216" />
    <field name="rcClip" type="TRect" visibility="public" size="16" offset="8" file="ATXPVS.pas" line="1217" />
  </struct>
  <pointer name="PDTBGOPTS" type="TDTBGOPTS" indircnt="1" file="ATXPVS.pas" line="1221" />
  <variable name="OpenThemeData" type="function(hwnd: Cardinal; pszClassList: PWideChar): Cardinal;" file="ATXPVS.pas" line="1225" />
  <variable name="CloseThemeData" type="function(hTheme: Cardinal): Cardinal;" file="ATXPVS.pas" line="1229" />
  <variable name="DrawThemeBackground" type="function(hTheme: Cardinal; hdc: HDC; iPartId: Integer; iStateId: Integer; pRect: PRect; pClipRect: PRect): Cardinal;" file="ATXPVS.pas" line="1232" />
  <variable name="DrawThemeBackgroundEx" type="function(hTheme: Cardinal; hdc: HDC; iPartId: Integer; iStateId: Integer; pRect: PRect; pOptions: PDTBGOPTS): Cardinal;" file="ATXPVS.pas" line="1240" />
  <variable name="DrawThemeText" type="function(hTheme: Cardinal; hdc: HDC; iPartId: Integer; iStateId: Integer; pszText: PWideChar; iCharCount: Integer; dwTextFlags: Integer; dwTextFlags2: Integer; pRect: PRect): Cardinal;" file="ATXPVS.pas" line="1248" />
  <variable name="GetThemeBackgroundContentRect" type="function(hTheme: Cardinal; hdc: HDC; iPartId: Integer; iStateId: Integer; pBoundingRect: PRect; pContentRect: TRect): Cardinal;" file="ATXPVS.pas" line="1259" />
  <variable name="GetThemeBackgroundExtent" type="function(hTheme: Cardinal; hdc: HDC; iPartId: Integer; iStateId: Integer; pContentRect: PRect; pExtentRect: TRect): Cardinal;" file="ATXPVS.pas" line="1267" />
  <variable name="GetThemeTextExtent" type="function(hTheme: Cardinal; hdc: HDC; iPartId: Integer; iStateId: Integer; pszText: PWideChar; iCharCount: Integer; dwTextFlags: Integer; pBoundingRect: PRect; pExtentRect: TRect): Cardinal;" file="ATXPVS.pas" line="1275" />
  <variable name="GetThemeTextMetrics" type="function(hTheme: Cardinal; hdc: HDC; iPartId: Integer; iStateId: Integer; ptm: tagTEXTMETRICW): Cardinal;" file="ATXPVS.pas" line="1286" />
  <variable name="GetThemeBackgroundRegion" type="function(hTheme: Cardinal; hdc: HDC; iPartId: Integer; iStateId: Integer; pRect: PRect; pRegion: HRGN): Cardinal;" file="ATXPVS.pas" line="1293" />
  <variable name="HitTestThemeBackground" type="function(hTheme: Cardinal; hdc: HDC; iPartId: Integer; iStateId: Integer; dwOptions: Integer; pRect: PRect; hrgn: HRGN; ptTest: Integer; pwHitTestCode: Word): Cardinal;" file="ATXPVS.pas" line="1301" />
  <variable name="DrawThemeEdge" type="function(hTheme: Cardinal; hdc: HDC; iPartId: Integer; iStateId: Integer; pDestRect: PRect; uEdge: Word; uFlags: Word; pContentRect: TRect): Cardinal;" file="ATXPVS.pas" line="1312" />
  <variable name="DrawThemeIcon" type="function(hTheme: Cardinal; hdc: HDC; iPartId: Integer; iStateId: Integer; pRect: PRect; himl: Cardinal; iImageIndex: Integer): Cardinal;" file="ATXPVS.pas" line="1322" />
  <variable name="IsThemePartDefined" type="function(hTheme: Cardinal; iPartId: Integer; iStateId: Integer): Integer;" file="ATXPVS.pas" line="1331" />
  <variable name="IsThemeBackGroundPartiallyTransparent" type="function(hTheme: Cardinal; iPartId: Integer; iStateId: Integer): Integer;" file="ATXPVS.pas" line="1336" />
  <variable name="GetThemeColor" type="function(hTheme: Cardinal; iPartId: Integer; iStateId: Integer; iPropId: Integer; pColor: TColor): Cardinal;" file="ATXPVS.pas" line="1341" />
  <variable name="GetThemeMetric" type="function(hTheme: Cardinal; hdc: HDC; iPartId: Integer; iStateId: Integer; iPropId: Integer; piVal: Integer): Cardinal;" file="ATXPVS.pas" line="1348" />
  <variable name="GetThemeString" type="function(hTheme: Cardinal; iPartId: Integer; iStateId: Integer; iPropId: Integer; pszBuff: PWideChar; cchMaxBuffChars: Integer): Cardinal;" file="ATXPVS.pas" line="1356" />
  <variable name="GetThemeBool" type="function(hTheme: Cardinal; iPartId: Integer; iStateId: Integer; iPropId: Integer; pfVal: LongBool): Cardinal;" file="ATXPVS.pas" line="1364" />
  <variable name="GetThemeInt" type="function(hTheme: Cardinal; iPartId: Integer; iStateId: Integer; iPropId: Integer; piVal: Integer): Cardinal;" file="ATXPVS.pas" line="1371" />
  <variable name="GetThemeEnumValue" type="function(hTheme: Cardinal; iPartId: Integer; iStateId: Integer; iPropId: Integer; piVal: Integer): Cardinal;" file="ATXPVS.pas" line="1378" />
  <variable name="GetThemePosition" type="function(hTheme: Cardinal; iPartId: Integer; iStateId: Integer; iPropId: Integer; pPoint: TPoint): Cardinal;" file="ATXPVS.pas" line="1385" />
  <variable name="GetThemeFont" type="function(hTheme: Cardinal; hdc: HDC; iPartId: Integer; iStateId: Integer; iPropId: Integer; pFont: tagLOGFONTW): Cardinal;" file="ATXPVS.pas" line="1392" />
  <variable name="GetThemeRect" type="function(hTheme: Cardinal; iPartId: Integer; iStateId: Integer; iPropId: Integer; pRect: TRect): Cardinal;" file="ATXPVS.pas" line="1400" />
  <variable name="GetThemeMargins" type="function(hTheme: Cardinal; hdc: HDC; iPartId: Integer; iStateId: Integer; iPropId: Integer; prc: TRect; pMargins: TRect): Cardinal;" file="ATXPVS.pas" line="1407" />
  <variable name="GetThemeIntList" type="function(hTheme: Cardinal; iPartId: Integer; iStateId: Integer; iPropId: Integer; pIntList: Pointer): Cardinal;" file="ATXPVS.pas" line="1416" />
  <variable name="SetWindowTheme" type="function(hwnd: HWND; pszSubAppName: PWideChar; pszSubIdList: PWideChar): Cardinal;" file="ATXPVS.pas" line="1423" />
  <variable name="GetThemeFilename" type="function(hTheme: Cardinal; iPartId: Integer; iStateId: Integer; iPropId: Integer; pszThemeFileName: PWideChar; cchMaxBuffChars: Integer): Cardinal;" file="ATXPVS.pas" line="1428" />
  <variable name="GetThemeSysColor" type="function(hTheme: Cardinal; iColorId: Integer): Integer;" file="ATXPVS.pas" line="1436" />
  <variable name="GetThemeSysColorBrush" type="function(hTheme: Cardinal; iColorId: Integer): Integer;" file="ATXPVS.pas" line="1440" />
  <variable name="GetThemeSysBool" type="function(hTheme: Cardinal; iBoolId: Integer): Integer;" file="ATXPVS.pas" line="1444" />
  <variable name="GetThemeSysSize" type="function(hTheme: Cardinal; iSizeId: Integer): Integer;" file="ATXPVS.pas" line="1448" />
  <variable name="GetThemeSysFont" type="function(hTheme: Cardinal; iFontId: Integer; plf: tagLOGFONTW): Cardinal;" file="ATXPVS.pas" line="1452" />
  <variable name="GetThemeSysString" type="function(hTheme: Cardinal; iStringId: Integer; pszStringBuff: PWideChar; cchMaxStringChars: Integer): Cardinal;" file="ATXPVS.pas" line="1457" />
  <variable name="GetThemeSysInt" type="function(hTheme: Cardinal; iIntId: Integer; piValue: Integer): Cardinal;" file="ATXPVS.pas" line="1463" />
  <variable name="IsThemeActive" type="function: LongBool;" file="ATXPVS.pas" line="1468" />
  <variable name="IsAppThemed" type="function: LongBool;" file="ATXPVS.pas" line="1471" />
  <variable name="GetWindowTheme" type="function(hwnd: HWND): Integer;" file="ATXPVS.pas" line="1474" />
  <variable name="EnableThemeDialogTexture" type="function(hwnd: HWND; dwFlags: Integer): Cardinal;" file="ATXPVS.pas" line="1477" />
  <variable name="IsThemeDialogTextureEnabled" type="function(hwnd: HWND): LongBool;" file="ATXPVS.pas" line="1481" />
  <variable name="GetThemeAppProperties" type="function: Cardinal;" file="ATXPVS.pas" line="1484" />
  <variable name="SetThemeAppProperties" type="function(dwFlags: Cardinal): Integer;" file="ATXPVS.pas" line="1487" />
  <variable name="GetCurrentThemeName" type="function(pszThemeFileName: PWideChar; cchMaxNameChars: Integer; pszColorBuff: PWideChar; cchMaxColorChars: Integer; pszSizeBuff: PWideChar; cchMaxSizeChars: Integer): Cardinal;" file="ATXPVS.pas" line="1490" />
  <variable name="GetThemeDocumentationProperty" type="function(pszThemeName: PWideChar; pszPropertyName: PWideChar; pszValueBuff: PWideChar; cchMaxValChars: Integer): Cardinal;" file="ATXPVS.pas" line="1498" />
  <variable name="DrawThemeParentBackground" type="function(hwnd: HWND; hdc: HDC; prc: TRect): Cardinal;" file="ATXPVS.pas" line="1504" />
  <variable name="EnableTheming" type="function(fEnable: LongBool): Cardinal;" file="ATXPVS.pas" line="1509" />
</namespace>
