<?xml version="1.0" encoding="utf-8"?>
<namespace name="UGenucht" platform="Win32">
  <const name="psimin" type="Comp" file="UGenucht.pas" line="19">
    <value>
      2
    </value>
  </const>
  <type name="real" type="Double" file="System.pas" line="12" />
  <class name="TGenucht" file="UGenucht.pas" line="24">
    <ancestor name="TObject" namespace="System">
      <methodref name="Create" visibility="public" procflags="constructor">
      </methodref>
      <methodref name="Free" visibility="public">
      </methodref>
      <methodref name="DisposeOf" visibility="public" procflags="inline" symflags="deprecated">
      </methodref>
      <methodref name="InitInstance" visibility="public" procflags="class">
      </methodref>
      <methodref name="CleanupInstance" visibility="public">
      </methodref>
      <methodref name="ClassType" visibility="public" procflags="inline">
      </methodref>
      <methodref name="ClassName" visibility="public" procflags="class">
      </methodref>
      <methodref name="ClassNameIs" visibility="public" procflags="class">
      </methodref>
      <methodref name="ClassParent" visibility="public" procflags="class inline">
      </methodref>
      <methodref name="ClassInfo" visibility="public" procflags="class inline">
      </methodref>
      <methodref name="InstanceSize" visibility="public" procflags="class inline">
      </methodref>
      <methodref name="InheritsFrom" visibility="public" procflags="class">
      </methodref>
      <methodref name="MethodAddress" visibility="public" procflags="class overload">
      </methodref>
      <methodref name="MethodAddress" visibility="public" procflags="class overload">
      </methodref>
      <methodref name="MethodName" visibility="public" procflags="class">
      </methodref>
      <methodref name="QualifiedClassName" visibility="public" procflags="class">
      </methodref>
      <methodref name="FieldAddress" visibility="public" procflags="overload">
      </methodref>
      <methodref name="FieldAddress" visibility="public" procflags="overload">
      </methodref>
      <methodref name="GetInterface" visibility="public">
      </methodref>
      <methodref name="GetInterfaceEntry" visibility="public" procflags="class">
      </methodref>
      <methodref name="GetInterfaceTable" visibility="public" procflags="class inline">
      </methodref>
      <methodref name="UnitName" visibility="public" procflags="class">
      </methodref>
      <methodref name="UnitScope" visibility="public" procflags="class">
      </methodref>
      <methodref name="Equals" visibility="public" procflags="virtual">
      </methodref>
      <methodref name="GetHashCode" visibility="public" procflags="virtual">
      </methodref>
      <methodref name="ToString" visibility="public" procflags="virtual">
      </methodref>
      <methodref name="SafeCallException" visibility="public" procflags="virtual">
      </methodref>
      <methodref name="AfterConstruction" visibility="public" procflags="virtual">
      </methodref>
      <methodref name="BeforeDestruction" visibility="public" procflags="virtual">
      </methodref>
      <methodref name="Dispatch" visibility="public" procflags="virtual">
      </methodref>
      <methodref name="DefaultHandler" visibility="public" procflags="virtual">
      </methodref>
      <methodref name="NewInstance" visibility="public" procflags="class virtual">
      </methodref>
      <methodref name="FreeInstance" visibility="public" procflags="virtual">
      </methodref>
      <methodref name="Destroy" visibility="public" procflags="destructor virtual">
      </methodref>
      <methodref name="GetDisposed" visibility="protected" procflags="inline">
      </methodref>
      <methodref name="CheckDisposed" visibility="protected" procflags="inline">
      </methodref>
      <propertyref name="Disposed" visibility="protected">
      </propertyref>
    </ancestor>
    <members>
      <field name="b_sat" type="Double" visibility="public" size="8" offset="8" file="UGenucht.pas" line="29">
        <devnotes>
           <summary>Water content at saturation [cm3/cm3].</summary>
        </devnotes>
      </field>
      <field name="b_rest" type="Double" visibility="public" size="8" offset="16" file="UGenucht.pas" line="32">
        <devnotes>
           <summary>Residual water content [cm3/cm3].</summary>
        </devnotes>
      </field>
      <field name="Ks" type="Double" visibility="public" size="8" offset="24" file="UGenucht.pas" line="35">
        <devnotes>
           <summary>Saturated hydraulic conductivity [cm/d].</summary>
        </devnotes>
      </field>
      <field name="alpha" type="Double" visibility="public" size="8" offset="32" file="UGenucht.pas" line="38">
        <devnotes>
           <summary>Fitting parameter &quot;alpha&quot; [1/cm].</summary>
        </devnotes>
      </field>
      <field name="n_par" type="Double" visibility="public" size="8" offset="40" file="UGenucht.pas" line="41">
        <devnotes>
           <summary>Dimensionless fitting parameter &quot;n&quot;.</summary>
        </devnotes>
      </field>
      <field name="m_par" type="Double" visibility="public" size="8" offset="48" file="UGenucht.pas" line="46">
        <devnotes>
           <summary>
           Fitting parameter &quot;m&quot; = 1-1/n (Mualem), 1-2/n (Burdine), or 1 (Vereecken).
           </summary>
        </devnotes>
      </field>
      <field name="l_par" type="Double" visibility="public" size="8" offset="56" file="UGenucht.pas" line="49">
        <devnotes>
           <summary>Fitting parameter &quot;l&quot;.</summary>
        </devnotes>
      </field>
      <function name="b_rel_f" visibility="public" file="UGenucht.pas" line="55">
        <devnotes>
           <summary>
           Calculates the relative water content from volumetric water content (b),
           residual water content (b_rest), and water content at saturation (b_sat).
           </summary>
        </devnotes>
        <parameters>
          <parameter name="b" type="Double" />
          <retval type="Double" />
        </parameters>
      </function>
      <function name="b_psi_f" visibility="public" file="UGenucht.pas" line="58">
        <devnotes>
           <summary>Calculates volumetric water content (b) from water tension (psi).</summary>
        </devnotes>
        <parameters>
          <parameter name="psi" type="Double" />
          <retval type="Double" />
        </parameters>
      </function>
      <function name="psi_b_f" visibility="public" file="UGenucht.pas" line="64">
        <devnotes>
           <summary>
           Calculates the absolute value of water tension (positive)
           from volumetric water content.
           </summary>
        </devnotes>
        <parameters>
          <parameter name="b" type="Double" />
          <retval type="Double" />
        </parameters>
      </function>
      <function name="Ku_b_f" visibility="public" file="UGenucht.pas" line="67">
        <devnotes>
           <summary>Calculates unsaturated hydraulic conductivity.</summary>
        </devnotes>
        <parameters>
          <parameter name="b" type="Double" />
          <retval type="Double" />
        </parameters>
      </function>
      <function name="Ku_psi_f" visibility="public" file="UGenucht.pas" line="70">
        <devnotes>
           <summary>Calculates unsaturated hydraulic conductivity.</summary>
        </devnotes>
        <parameters>
          <parameter name="psi" type="Double" />
          <retval type="Double" />
        </parameters>
      </function>
      <function name="C_b_f" visibility="public" file="UGenucht.pas" line="73">
        <devnotes>
           <summary>Calculates specific water storage capacity.</summary>
        </devnotes>
        <parameters>
          <parameter name="b" type="Double" />
          <retval type="Double" />
        </parameters>
      </function>
      <function name="C_psi_f" visibility="public" file="UGenucht.pas" line="76">
        <devnotes>
           <summary>Calculates specific water storage capacity.</summary>
        </devnotes>
        <parameters>
          <parameter name="psi" type="Double" />
          <retval type="Double" />
        </parameters>
      </function>
      <function name="Dw_f" visibility="public" file="UGenucht.pas" line="79">
        <devnotes>
           <summary>Calculates water diffusivity.</summary>
        </devnotes>
        <parameters>
          <parameter name="b" type="Double" />
          <retval type="Double" />
        </parameters>
      </function>
      <function name="b_rel_psi_f" visibility="public" file="UGenucht.pas" line="82">
        <devnotes>
           <summary>Calculates relative water content from water tension &quot;psi&quot;.</summary>
        </devnotes>
        <parameters>
          <parameter name="psi" type="Double" />
          <retval type="Double" />
        </parameters>
      </function>
    </members>
  </class>
</namespace>
